# 字节码
- 了解 JVM 底层实际处理的原理；
- 了解 JVM 特性；

# 工具
1. Jdk：javac 编译和 javap反编译；
2. jclasslib：字节码阅读工具。
3. javac 和 javap 使用，参考 `javap --help`和 `javac --help`

# example
## jdk版本：

```
$ java -version
java version "1.8.0_77"
Java(TM) SE Runtime Environment (build 1.8.0_77-b03)
Java HotSpot(TM) 64-Bit Server VM (build 25.77-b03, mixed mode)
```

## Sourcecode

```java
public class StringTest{
	public static void main(String[] args) {
        String a = "hello";
        String c = a+2;
        String d = a+2;
        System.out.println(c==d);
    }
}
```

## Bytecode
使用 `javap -verbose StringTest.class` 得到字节码详细信息：
```java
Classfile /E:/00justin/04-Project/justin/examples/primitive-demo/javaBase/StringTest.class
  Last modified 2021-9-11; size 768 bytes
  MD5 checksum 73f23aa1da4b3820e4758013e89a8164
  Compiled from "StringTest.java"
public class StringTest
  minor version: 0  //次版本
  major version: 52 //主版本
  flags: ACC_PUBLIC, ACC_SUPER   //访问标记
Constant pool: // 常量池
   #1 = Methodref          #11.#24        // java/lang/Object."<init>":()V
   #2 = String             #25            // hello
   #3 = Class              #26            // java/lang/StringBuilder
   #4 = Methodref          #3.#24         // java/lang/StringBuilder."<init>":()V
   #5 = Methodref          #3.#27         // java/lang/StringBuilder.append:(Ljava/lang/String;)Ljava/lang/StringBuilder;
   #6 = Methodref          #3.#28         // java/lang/StringBuilder.append:(I)Ljava/lang/StringBuilder;
   #7 = Methodref          #3.#29         // java/lang/StringBuilder.toString:()Ljava/lang/String;
   #8 = Fieldref           #30.#31        // java/lang/System.out:Ljava/io/PrintStream;
   #9 = Methodref          #32.#33        // java/io/PrintStream.println:(Z)V
  #10 = Class              #34            // StringTest
  #11 = Class              #35            // java/lang/Object
  #12 = Utf8               <init>
  #13 = Utf8               ()V
  #14 = Utf8               Code
  #15 = Utf8               LineNumberTable
  #16 = Utf8               main
  #17 = Utf8               ([Ljava/lang/String;)V
  #18 = Utf8               StackMapTable
  #19 = Class              #36            // "[Ljava/lang/String;"
  #20 = Class              #37            // java/lang/String
  #21 = Class              #38            // java/io/PrintStream
  #22 = Utf8               SourceFile
  #23 = Utf8               StringTest.java
  #24 = NameAndType        #12:#13        // "<init>":()V
  #25 = Utf8               hello
  #26 = Utf8               java/lang/StringBuilder
  #27 = NameAndType        #39:#40        // append:(Ljava/lang/String;)Ljava/lang/StringBuilder;
  #28 = NameAndType        #39:#41        // append:(I)Ljava/lang/StringBuilder;
  #29 = NameAndType        #42:#43        // toString:()Ljava/lang/String;
  #30 = Class              #44            // java/lang/System
  #31 = NameAndType        #45:#46        // out:Ljava/io/PrintStream;
  #32 = Class              #38            // java/io/PrintStream
  #33 = NameAndType        #47:#48        // println:(Z)V
  #34 = Utf8               StringTest
  #35 = Utf8               java/lang/Object
  #36 = Utf8               [Ljava/lang/String;
  #37 = Utf8               java/lang/String
  #38 = Utf8               java/io/PrintStream
  #39 = Utf8               append
  #40 = Utf8               (Ljava/lang/String;)Ljava/lang/StringBuilder;
  #41 = Utf8               (I)Ljava/lang/StringBuilder;
  #42 = Utf8               toString
  #43 = Utf8               ()Ljava/lang/String;
  #44 = Utf8               java/lang/System
  #45 = Utf8               out
  #46 = Utf8               Ljava/io/PrintStream;
  #47 = Utf8               println
  #48 = Utf8               (Z)V
{
  public StringTest();   // 类构造函数
    descriptor: ()V      // 描述符
    flags: ACC_PUBLIC    // 访问标志
    Code:                // 字节码区
      stack=1, locals=1, args_size=1 // stack:最大栈帧深度；locals：局部变量所需存储空间；args_size：参数个数
         0: aload_0
         1: invokespecial #1    // Method java/lang/Object."<init>":()V
         4: return
      LineNumberTable: // 源码行号和字节码行号映射
        line 1: 0

  public static void main(java.lang.String[]);
    descriptor: ([Ljava/lang/String;)V
    flags: ACC_PUBLIC, ACC_STATIC
    Code:
      stack=3, locals=4, args_size=1
         0: ldc           #2                  // String hello
         2: astore_1
         3: new           #3                  // class java/lang/StringBuilder
         6: dup
         7: invokespecial #4                  // Method java/lang/StringBuilder."<init>":()V
        10: aload_1
        11: invokevirtual #5                  // Method java/lang/StringBuilder.append:(Ljava/lang/String;)Ljava/lang/StringBuilder;
        14: iconst_2
        15: invokevirtual #6                  // Method java/lang/StringBuilder.append:(I)Ljava/lang/StringBuilder;
        18: invokevirtual #7                  // Method java/lang/StringBuilder.toString:()Ljava/lang/String;
        21: astore_2
        22: new           #3                  // class java/lang/StringBuilder
        25: dup
        26: invokespecial #4                  // Method java/lang/StringBuilder."<init>":()V
        29: aload_1
        30: invokevirtual #5                  // Method java/lang/StringBuilder.append:(Ljava/lang/String;)Ljava/lang/StringBuilder;
        33: iconst_2
        34: invokevirtual #6                  // Method java/lang/StringBuilder.append:(I)Ljava/lang/StringBuilder;
        37: invokevirtual #7                  // Method java/lang/StringBuilder.toString:()Ljava/lang/String;
        40: astore_3
        41: getstatic     #8                  // Field java/lang/System.out:Ljava/io/PrintStream;
        44: aload_2
        45: aload_3
        46: if_acmpne     53
        49: iconst_1
        50: goto          54
        53: iconst_0
        54: invokevirtual #9                  // Method java/io/PrintStream.println:(Z)V
        57: return
      LineNumberTable:
        line 3: 0
        line 4: 3
        line 5: 22
        line 6: 41
        line 7: 57
      StackMapTable: number_of_entries = 2
        frame_type = 255 /* full_frame */
          offset_delta = 53
          locals = [ class "[Ljava/lang/String;", class java/lang/String, class java/lang/String, class java/lang/String ]
          stack = [ class java/io/PrintStream ]
        frame_type = 255 /* full_frame */
          offset_delta = 0
          locals = [ class "[Ljava/lang/String;", class java/lang/String, class java/lang/String, class java/lang/String ]
          stack = [ class java/io/PrintStream, int ]
}
SourceFile: "StringTest.java"
```

## 理解
可以看到，String的“+”操作实际执行的是：`new StringBuilder().append("hello").append("2").toString()`. 查看 StringBuilder 的源码，可知 toString() 的实现是：
```java
@Override  
public String toString() {  
    // Create a copy, don't share the array  
 return new String(value, 0, count);  
}
```

**新建**了一个 String 对象，所以c和d是两个不同的对象，"c\=\=d"是false.



# 参考
1. [[Hotspot 字节码指令集]]
2. [[Java 和 Major 版本对照表]]
3. [[字节码字段描述符]]
4. [[字节码访问标志]]